[{"title": "Essentials of metalworking; a textbook for schools and shops, by Edward Berg and Bristol E. Wing, illustrations by Ray J. Matasek.", "author": "Berg, Edward.", "id": "9127003"}, {"title": "Instructional units in woodfinishing [by] R. A. McGee ... and Arthur G. Brown ...", "author": "McGee, Richard Allen, 1897-", "id": "9127006"}, {"title": "Meal service, by Charlotte Halgrim and Maurine Canon.", "author": "Halgrim, Charlotte.", "id": "102748963"}, {"title": "When mother lets us sew, by Virginia Ralston", "author": "Ralston, Virginia Mrs. 1870-", "id": "1518314"}, {"title": "Reconstruction of industrial arts courses, with especial reference to aims and objectives in junior high schools,", "author": "Snedden, David, 1868-1951.", "id": "1045953"}, {"title": "American blacksmith and motor shop.", "author": "", "id": "499425"}, {"title": "American blacksmith and motor shop.", "author": "", "id": "499425"}, {"title": "American blacksmith and motor shop.", "author": "", "id": "499425"}, {"title": "American blacksmith and motor shop.", "author": "", "id": "499425"}, {"title": "American blacksmith and motor shop.", "author": "", "id": "499425"}, {"title": "American blacksmith and motor shop.", "author": "", "id": "499425"}, {"title": "American blacksmith and motor shop.", "author": "", "id": "499425"}, {"title": "American blacksmith and motor shop.", "author": "", "id": "499425"}, {"title": "American blacksmith and motor shop.", "author": "", "id": "499425"}, {"title": "American blacksmith and motor shop.", "author": "", "id": "499425"}, {"title": "American blacksmith and motor shop.", "author": "", "id": "499425"}, {"title": "National painters magazine.", "author": "", "id": "548324"}, {"title": "Handcraft for home, school, playground and summer camp.", "author": "National Recreation Association.", "id": "100823135"}, {"title": "Antique iron works and machines of the water power age.", "author": "Schultz, George Winterhalter.", "id": "9429810"}, {"title": "Reconstruction of industrial arts courses, with especial reference to aims and objectives in junior high schools,", "author": "Snedden, David, 1868-1951.", "id": "1045953"}, {"title": "A guide to laundry-work; a manual for home and school, by Mary D. Chambers.", "author": "Chambers, Mary Davoren (Molony) Mrs., 1864-", "id": "6562794"}, {"title": "Reconstruction of industrial arts courses, with especial reference to aims and objectives in junior high schools,", "author": "Snedden, David, 1868-1951.", "id": "1045953"}, {"title": "The boy's busy book, by Chelsea Fraser ... with numerous drawings and special photographs by the author.", "author": "Fraser, Chelsea Curtis, 1876-", "id": "6577823"}, {"title": "Wood working industries", "author": "", "id": "10328493"}, {"title": "Petit manuel de dorure sur bois.", "author": "Wandenberg, Eug\u00e8ne.", "id": "102064797"}]