[{"title": "Bindingsvaerk; jydske digte.", "author": "Berntsen, Anton, 1873-", "id": "1427087"}, {"title": "\u00f8stergaard og Vestergaard; lystapil med sange i 3 akter. For dilettanter.", "author": "L\u00f8kken, Thomas Olesen, 1877-1955.", "id": "1427282"}, {"title": "Povl Dam ...", "author": "L\u00f8kken, Thomas Olesen, 1877-1955.", "id": "1427288"}, {"title": "Povl Dam ...", "author": "L\u00f8kken, Thomas Olesen, 1877-1955.", "id": "1427288"}, {"title": "Povl Dam ...", "author": "L\u00f8kken, Thomas Olesen, 1877-1955.", "id": "1427288"}, {"title": "Thomas Olesen L\u00f8kken; en dansk folkelivsskildrer. Omslag og vignetter af Lars Nielsen.", "author": "Bukdahl, J\u00f8rgen, 1896-", "id": "1427304"}, {"title": "De kloge koner i Vindblaes; Maren Haaning.", "author": "Rasmussen, Louise.", "id": "1427334"}, {"title": "L'ours polaire, nouvelle. Tr. du danois par Mme. Ren\u00e9guy. Illustrations de Ren\u00e9-George Gauthier.", "author": "Pontoppidan, Henrik, 1857-1943.", "id": "1788897"}, {"title": "Den uerfarne rejensende;", "author": "Gunnarsson, Gunnar, 1889-1975.", "id": "1200523"}, {"title": "Krotov\u02b9i kochki : rasskazy / Martin Andersen Nekse\u0307.", "author": "Andersen Nex\u00f8, Martin, 1869-1954.", "id": "102770178"}, {"title": "Tredive aar paa det danske Parnas / Palle Rosenkrantz.", "author": "Rosenkrantz, Palle, baron, 1867-1941.", "id": "6622190"}, {"title": "Thomas Olesen L\u00f8kken; en dansk folkelivsskildrer. Omslag og vignetter af Lars Nielsen.", "author": "Bukdahl, J\u00f8rgen, 1896-", "id": "1427304"}, {"title": "Min h\u00e6dersdag paa Kj\u00f8benhavns Raadhus 10. September 1926.", "author": "Aakj\u00e6r, Jeppe, 1866-1930.", "id": "6623987"}, {"title": "Kulturaben.", "author": "Clausen, Sven M.", "id": "6624051"}, {"title": "Den gamle historie, skuespil i 3 akter.", "author": "Clausen, Sven, 1893-1961.", "id": "6624052"}, {"title": "Titania holdt bryllup : digte / Sophus Claussen.", "author": "Claussen, Sophus, 1865-1931.", "id": "6624084"}, {"title": "Manden paa H\u00f8rsholm.", "author": "Rosenkrantz, Palle, baron, 1867-1941.", "id": "7372032"}, {"title": "Da H.C. Andersen kom til Strinthus, noveller og beretninger.", "author": "Waagner, William.", "id": "6103959"}, {"title": "Selvforsvar og landevaern.", "author": "Nielsen, Harald Charles Christian Anton, 1879-1957.", "id": "101793312"}, {"title": "Sang for alle Vinde.", "author": "Bergstedt, Harald, 1877-1965.", "id": "7079757"}, {"title": "Under aftenstjaernen; digte.", "author": "Aakj\u00e6r, Jeppe, 1866-1930.", "id": "7079590"}, {"title": "Det ra\u0308tta ansiktet och andra noveller.", "author": "Ho\u0308gstro\u0308m-Lo\u0308fberg, Elisabeth, 1894-", "id": "7080985"}, {"title": "Noveller / Otto Rung.", "author": "Rung, Otto, 1874-1945.", "id": "7082425"}, {"title": "Jacob Paludan.", "author": "Hallar, S\u00f8ren Christian, 1887-", "id": "7082203"}, {"title": "Feodor Jansens jeremiader, ved Jacob Paludan.", "author": "Paludan, Jacob, 1896-", "id": "7082177"}, {"title": "Tr\u00e6kfuglevej, fort\u00e6llinger og digte.", "author": "Larsen, Th\u00f8ger, 1875-1928.", "id": "7081793"}, {"title": "K\u00f8benhavnske poesier; digte.", "author": "B\u00f8nnelycke, Emil, 1893-1953.", "id": "7079922"}, {"title": "Rotka\u0308ppchen. Autorisierte U\u0308bersetzung von Mathilde Mann.  Mit einem Nachwort von Dr. Elias.", "author": "Pontoppidan, Henrik, 1857-1943.", "id": "7082254"}, {"title": "Bez ustoev : roman / Gudmundur Kamban ; perevod s datskogo A.V. Ganzen.", "author": "Gu\u00f0mundur Kamban, 1888-1945.", "id": "7081559"}, {"title": "Den blinde rytter.", "author": "Bregendahl, Marie, 1867-1940.", "id": "7079962"}, {"title": "Foraarstaler / Sophus Claussen.", "author": "Claussen, Sophus, 1865-1931.", "id": "7080437"}, {"title": "Rejsen til Astrid : digte / Otto Gelsted.", "author": "Gelsted, Otto, 1888-1968.", "id": "7080619"}, {"title": "Ringen / Laurids Bruun.", "author": "Bruun, Laurids, 1864-1935.", "id": "7288554"}, {"title": "Markerne modnes; roman.", "author": "Paludan, Jacob, 1896-", "id": "8553921"}, {"title": "I dagningen; digte.", "author": "Seedorff Pedersen, Hans Hartvig, b. 1892.", "id": "8554033"}, {"title": "Verdslige sange, digte. Tegninger af Carl Jensen.", "author": "Kristensen, Tom, 1893-1974.", "id": "8552976"}, {"title": "Den galliske sommer, digte.", "author": "La Cour, Paul, 1902-1956.", "id": "8552904"}]