[{"title": "History of the Willamette Valley, Oregon, by Robert Carlton Clark : [publisher's announcement / S.J. Clarke Publishing Co.].", "author": "S.J. Clarke Publishing Company.", "id": "6000258"}, {"title": "Oregon historical quarterly.", "author": "", "id": "495101"}, {"title": "Rules and regulations, Crater lake national park,", "author": "United States. National Park Service.", "id": "1719208"}, {"title": "Rules and regulations, Crater lake national park,", "author": "United States. National Park Service.", "id": "1719208"}, {"title": "Rules and regulations, Crater lake national park,", "author": "United States. National Park Service.", "id": "1719208"}, {"title": "Rules and regulations, Crater lake national park,", "author": "United States. National Park Service.", "id": "1719208"}, {"title": "Rules and regulations, Crater lake national park,", "author": "United States. National Park Service.", "id": "1719208"}, {"title": "Rules and regulations, Crater lake national park,", "author": "United States. National Park Service.", "id": "1719208"}, {"title": "Rules and regulations, Crater lake national park,", "author": "United States. National Park Service.", "id": "1719208"}, {"title": "Rules and regulations, Crater lake national park,", "author": "United States. National Park Service.", "id": "1719208"}, {"title": "Directory of licensed real estate brokers and salesmen.", "author": "", "id": "7375497"}, {"title": "Directory of licensed real estate brokers and salesmen.", "author": "", "id": "7375497"}, {"title": "Marcus Whitman : hero of the Oregon country / program prepared by Floyd L. Carr.", "author": "Carr, Floyd L.", "id": "102809990"}, {"title": "Oregon historical quarterly.", "author": "Oregon Historical Society.", "id": "9783483"}, {"title": "History of the Willamette valley, Oregon / by Robert Carlton Clark.", "author": "Clark, Robert Carlton, 1877-1939.", "id": "100959264"}, {"title": "History of the Willamette valley, Oregon / by Robert Carlton Clark.", "author": "Clark, Robert Carlton, 1877-1939.", "id": "100959264"}, {"title": "History of the Willamette valley, Oregon / by Robert Carlton Clark.", "author": "Clark, Robert Carlton, 1877-1939.", "id": "100959264"}, {"title": "Oregon historical quarterly.", "author": "Oregon Historical Society.", "id": "9783483"}]