[{"title": "Byzantinische Zeitschrift.", "author": "", "id": "517554"}, {"title": "Byzantinische Zeitschrift.", "author": "", "id": "517554"}, {"title": "Ta h\u014draiotera d\u0113motika tragoudia t\u0113s agap\u0113s / eklog\u0113 Ge\u014drgiou Drosin\u0113.,\u03a4\u03b1 \u03c9\u03c1\u03b1\u03b9\u03bf\u03c4\u03b5\u03c1\u03b1 \u03b4\u03b7\u03bc\u03bf\u03c4\u03b9\u03ba\u03b1 \u03c4\u03c1\u03b1\u03b3\u03bf\u03c5\u03b4\u03b9\u03b1 \u03c4\u03b7\u03c2 \u03b1\u03b3\u03b1\u03c0\u03b7\u03c2 / \u03b5\u03ba\u03bb\u03bf\u03b3\u03b7 \u0393\u03b5\u03c9\u03c1\u03b3\u03b9\u03bf\u03c5 \u0394\u03c1\u03bf\u03c3\u03b9\u03bd\u03b7.", "author": "", "id": "5181567"}]