[{"title": "The official year book of New South Wales.", "author": "New South Wales. Bureau of Statistics and Economics.", "id": "547248"}, {"title": "In savage Australia; an account of a hunting and collecting expedition to Arnhem Land and Dampier Land. by Knut Dahl ... With photographs and drawings by the author and a foreword by Fridtjof Nansen.", "author": "Dahl, Knut, 1871-", "id": "1873147"}, {"title": "Journal and proceedings - Royal Australian Historical Society.", "author": "Royal Australian Historical Society.", "id": "517441"}, {"title": "The Australian encyclop\u00e6dia; edited by Arthur Wilberforce Jose ... and Herbert James Carter ...", "author": "", "id": "1873122"}, {"title": "The Australian encyclop\u00e6dia; edited by Arthur Wilberforce Jose ... and Herbert James Carter ...", "author": "", "id": "1873122"}, {"title": "A story of the Australian people.", "author": "Cramp, Karl Reginald, 1878-", "id": "1873175"}, {"title": "Victorian year book.", "author": "", "id": "2130212"}, {"title": "Journal of the Royal Australian Historical Society.", "author": "Royal Australian Historical Society.", "id": "100575222"}, {"title": "Journal of the Royal Australian Historical Society.", "author": "Royal Australian Historical Society.", "id": "100575222"}, {"title": "Official Yearbook of New South Wales", "author": "New South Wales. Bureau of Statistics and Economics.", "id": "10031920"}]