[{"title": "Unknown Sweden,", "author": "Steveni, William Barnes, 1859-", "id": "1235945"}, {"title": "Diplomatiska brev fra\u030an Stockholm; en brevva\u0308xling mellan herr Henri de Pallie\u0300res vid franska republikens legation i Stockholm och herr Raymond Constan vid utrikesministeriet i Paris, oktober 1925-september 1926.", "author": "Pallie\u0300res, Henri de.", "id": "5750976"}, {"title": "Sweden / with illustrations by A. Heaton Cooper", "author": "Heathcote, Dudley", "id": "102692892"}, {"title": "Diplomatiska brev fra\u030an Stockholm; en brevva\u0308xling mellan herr Henri de Pallie\u0300res vid franska republikens legation i Stockholm och herr Raymond Constan vid utrikesministeriet i Paris, oktober 1925-september 1926.", "author": "Pallie\u0300res, Henri de.", "id": "5750976"}]