[{"title": "Jingi shiry\u014d / Kurita Hiroshi chojutsu Kurita Tsutomu k\u014dtei.,\u795e\u7947\u5fd7\u6599 \u6817\u7530\u5bec\u8457\u8ff0 \u6817\u7530\u52e4\u6821\u8a02.", "author": "Kurita, Hiroshi, 1835-1899, \u6817\u7530\u5bec, 1835-1899.", "id": "2255564"}, {"title": "Jingi shiry\u014d / Kurita Hiroshi chojutsu Kurita Tsutomu k\u014dtei.,\u795e\u7947\u5fd7\u6599 \u6817\u7530\u5bec\u8457\u8ff0 \u6817\u7530\u52e4\u6821\u8a02.", "author": "Kurita, Hiroshi, 1835-1899, \u6817\u7530\u5bec, 1835-1899.", "id": "2255564"}, {"title": "Jingi shiry\u014d / Kurita Hiroshi chojutsu Kurita Tsutomu k\u014dtei.,\u795e\u7947\u5fd7\u6599 \u6817\u7530\u5bec\u8457\u8ff0 \u6817\u7530\u52e4\u6821\u8a02.", "author": "Kurita, Hiroshi, 1835-1899, \u6817\u7530\u5bec, 1835-1899.", "id": "2255564"}, {"title": "Jingi shiry\u014d / Kurita Hiroshi chojutsu Kurita Tsutomu k\u014dtei.,\u795e\u7947\u5fd7\u6599 \u6817\u7530\u5bec\u8457\u8ff0 \u6817\u7530\u52e4\u6821\u8a02.", "author": "Kurita, Hiroshi, 1835-1899, \u6817\u7530\u5bec, 1835-1899.", "id": "2255564"}, {"title": "Jinja Ky\u014dkai zasshi / Jinja Ky\u014dkai hen.,\u795e\u793e\u5354\u6703\u96dc\u8a8c / \u795e\u793e\u5354\u4f1a\u7de8.", "author": "", "id": "801514"}, {"title": "Le Shintoi\u0308sme : religion nationale.", "author": "Martin, J. M.", "id": "6551437"}, {"title": "Jingi shiryo\u0304 fuko\u0304 : [16-kan] / Kurita Hiroshi henshu\u0304 ; [Kurita] Tsutomu ko\u0304tei.,\u795e\u7947\u5fd7\u6599\u9644\u8003 : [16\u5377] / \u6817\u7530\u5bec\u7de8\u8f2f ; [\u6817\u7530]\u52e4\u6821\u8a02.", "author": "Kurita, Hiroshi, 1835-1899., \u6817\u7530\u5bec, 1835-1899.", "id": "9186437"}, {"title": "Jingi shiryo\u0304 fuko\u0304 : [16-kan] / Kurita Hiroshi henshu\u0304 ; [Kurita] Tsutomu ko\u0304tei.,\u795e\u7947\u5fd7\u6599\u9644\u8003 : [16\u5377] / \u6817\u7530\u5bec\u7de8\u8f2f ; [\u6817\u7530]\u52e4\u6821\u8a02.", "author": "Kurita, Hiroshi, 1835-1899., \u6817\u7530\u5bec, 1835-1899.", "id": "9186437"}, {"title": "Jingi shiryo\u0304 fuko\u0304 : [16-kan] / Kurita Hiroshi henshu\u0304 ; [Kurita] Tsutomu ko\u0304tei.,\u795e\u7947\u5fd7\u6599\u9644\u8003 : [16\u5377] / \u6817\u7530\u5bec\u7de8\u8f2f ; [\u6817\u7530]\u52e4\u6821\u8a02.", "author": "Kurita, Hiroshi, 1835-1899., \u6817\u7530\u5bec, 1835-1899.", "id": "9186437"}, {"title": "Jingi shiryo\u0304 : [21-kan] / Kurita Hiroshi chojutsu ; [Kurita Tsutomu ko\u0304tei],\u795e\u7947\u5fd7\u6599 : [21\u5377] / \u6817\u7530\u5bec\u8457\u8ff0 ; [\u6817\u7530\u52e4\u6821\u8a02]", "author": "Kurita, Hiroshi, 1835-1899., \u6817\u7530\u5bec, 1835-1899.", "id": "9186429"}, {"title": "Jingi shiryo\u0304 : [21-kan] / Kurita Hiroshi chojutsu ; [Kurita Tsutomu ko\u0304tei],\u795e\u7947\u5fd7\u6599 : [21\u5377] / \u6817\u7530\u5bec\u8457\u8ff0 ; [\u6817\u7530\u52e4\u6821\u8a02]", "author": "Kurita, Hiroshi, 1835-1899., \u6817\u7530\u5bec, 1835-1899.", "id": "9186429"}]