[{"title": "Properties and testing of magnetic materials, by Thomas Spooner.", "author": "Spooner, Thomas, b. 1884.", "id": "1484838"}, {"title": "Applied magnetism, by T. F. Wall ...", "author": "Wall, Thomas Frederick, 1883-", "id": "1993773"}, {"title": "Properties and testing of magnetic materials, by Thomas Spooner.", "author": "Spooner, Thomas, b. 1884.", "id": "1484838"}, {"title": "Determination of the magnetic induction in sheet steel / by Raymond L. Sanford, physicist [and] James M. Barry, scientific aid, Bureau of Standards. February 17, 1927.", "author": "Sanford, Raymond Laraway, 1884-", "id": "9488693"}, {"title": "Magnetic reluctivity relationship / by Raymond L. Sanford, physicist, Bureau of Standards. February 17, 1927.", "author": "Sanford, Raymond Laraway, 1884-", "id": "9488694"}, {"title": "Properties and testing of magnetic materials, by Thomas Spooner.", "author": "Spooner, Thomas, b. 1884.", "id": "1484838"}, {"title": "Applied magnetism, by T. F. Wall ...", "author": "Wall, Thomas Frederick, 1883-", "id": "1993773"}, {"title": "Applied magnetism, by T. F. Wall ...", "author": "Wall, Thomas Frederick, 1883-", "id": "1993773"}, {"title": "Properties and testing of magnetic materials, by Thomas Spooner.", "author": "Spooner, Thomas, b. 1884.", "id": "1484838"}, {"title": "Applied magnetism, by T. F. Wall ...", "author": "Wall, Thomas Frederick, 1883-", "id": "1993773"}]