[{"title": "Valencia.", "author": "", "id": "102674123"}, {"title": "Paquimeres i Muntaner / per A. Rubio\u0301 i Lluch.", "author": "Rubio\u0301 y Lluch, Antonio, 1856-1937.", "id": "6037135"}, {"title": "L'urna d'argent de Sant Ermengol bisbe d'Urgell / per Pere Pujol i Tubau.", "author": "Pujol i Tubau, Pere.", "id": "6037136"}, {"title": "Documents hebraics de jueus catalans, per J. Milla\u0300s i Vallicrosa ...", "author": "Milla\u0301s Vallicrosa, Jose\u0301 Mari\u0301a, 1897-", "id": "6037134"}, {"title": "The Balearics and their peoples. With 2 maps and 42 illustrations.", "author": "Chamberlin, Frederick, 1870-1943.", "id": "1237317"}, {"title": "In the heart of Spain [by] Thomas Ewing Moore.", "author": "Moore, Thomas Ewing, b. 1867.", "id": "1237299"}, {"title": "Barcelona; Barcelona, the old city,", "author": "International Telephone and Telegraph Corporation.", "id": "1237326"}, {"title": "Historia sint\u00e9tica de Galicia,", "author": "Villar Ponte, Ram\u00f3n.", "id": "1237430"}, {"title": "Catalan separatism,", "author": "", "id": "1237406"}, {"title": "Die strasse von Gibraltar,", "author": "Jessen, Otto, 1891-", "id": "1286336"}, {"title": "No\u0301s.", "author": "", "id": "102840791"}, {"title": "Por la concordia.", "author": "Cambo\u0301, Francesc, 1876-1947.", "id": "6511207"}, {"title": "Santander, by E. Allison Peers.", "author": "Peers, E. Allison 1891-1952.", "id": "6527201"}, {"title": "Nuestras montan\u0303as; notas de alpinismo vizcai\u0301no, por A. Ferrer (el Hombre de las cavernas) ...", "author": "Ferrer, A.", "id": "6527220"}, {"title": "In the heart of Spain [by] Thomas Ewing Moore.", "author": "Moore, Thomas Ewing, b. 1867.", "id": "1237299"}, {"title": "Wandering among forgotten isles, by Jesse Metcalf; with a chapter on the scientific results of the cruise, by Robert Cushman Murphy.", "author": "Metcalf, Jesse, 1887-", "id": "6086563"}, {"title": "Mallorca the magnificent [by] Nina Larrey Duryea ... with an introduction by Ralph Adams Cram.", "author": "Duryea, Nina Larrey (Smith) Mrs. 1874-", "id": "6086573"}, {"title": "Gui\u0301a turista de la provincia de Valencia.", "author": "Sarthou Carreres, Carlos, 1876-1971.", "id": "6088735"}, {"title": "Bolet\u00edn de la Real Academia Gallega.", "author": "", "id": "7854257"}, {"title": "Las Jurdes; etude de geographie humaine.", "author": "Legendre, Maurice.", "id": "9517503"}, {"title": "Geograf\u00eda general del Reino de Valencia / dirigida por Francisco Carreras y Candi.", "author": "", "id": "100500446"}, {"title": "Geograf\u00eda general del Reino de Valencia / dirigida por Francisco Carreras y Candi.", "author": "", "id": "100500446"}, {"title": "Relaciones de pueblos del obispado de Cuenca, hechas por orden de Felipe II ... las publica, conforme a los originales de la Biblioteca de el Escorial, con introducci\u00f3n, notas, ap\u00e9ndices e \u00edndices, el P. Fr. Eusebio-Juli\u00e1n Zarco-Bacas y Cuevas ...", "author": "Zarco-Bacas y Cuevas, Eusebio-Juli\u00e1n, 1887-1936.", "id": "102623690"}, {"title": "Geograf\u00eda general del Reino de Valencia / dirigida por Francisco Carreras y Candi.", "author": "", "id": "100500446"}, {"title": "Geograf\u00eda general del Reino de Valencia / dirigida por Francisco Carreras y Candi.", "author": "", "id": "100500446"}, {"title": "Relaciones de pueblos del obispado de Cuenca, hechas por orden de Felipe II ... las publica, conforme a los originales de la Biblioteca de el Escorial, con introducci\u00f3n, notas, ap\u00e9ndices e \u00edndices, el P. Fr. Eusebio-Juli\u00e1n Zarco-Bacas y Cuevas ...", "author": "Zarco-Bacas y Cuevas, Eusebio-Juli\u00e1n, 1887-1936.", "id": "102623690"}, {"title": "Por la concordia.", "author": "Cambo\u0301, Francesc, 1876-1947.", "id": "6511207"}, {"title": "Ein Pyrena\u0308enbuch. Mit 33 abbildungen.", "author": "Tucholsky, Kurt, 1890-1935.", "id": "10975499"}, {"title": "In the heart of Spain [by] Thomas Ewing Moore.", "author": "Moore, Thomas Ewing, b. 1867.", "id": "1237299"}, {"title": "Mallorca the magnificent [by] Nina Larrey Duryea ... with an introduction by Ralph Adams Cram.", "author": "Duryea, Nina Larrey (Smith) Mrs. 1874-", "id": "6086573"}]