[{"title": "Ritsafn; s\u00f6gur--kv\u00e6\u00f0i--fyrirlestrar--bla\u00f0agreinir. Me\u00f0 ritger\u00f0 um h\u00f6fundinn, eftir Einar H. Kvaran.", "author": "Gestur P\u00e1lsson, 1852-1891.", "id": "1787302"}, {"title": "S\u00e1lin vaknar; b\u00e1ttur \u00far s\u00f6gu \u00e6skumanns.", "author": "Einar Hj\u00f6rleifsson Kvaran, 1859-1938.", "id": "1787261"}, {"title": "Brudekjolen : roman fra Island / Kristmann Gudmundsson.", "author": "Kristmann Gu\u00f0mundsson, 1901-1983.", "id": "6622225"}]