[{"title": "Report of the Engineering Board of Review of the Sanitary District of Chicago on the lake lowering controversy and a program of remedial measures. Part [I]-III.", "author": "Chicago Sanitary District. Engineering Board of Review.", "id": "9205703"}, {"title": "Publication.", "author": "", "id": "546485"}, {"title": "Publication.", "author": "", "id": "546485"}, {"title": "Publication.", "author": "", "id": "546485"}, {"title": "Publication.", "author": "", "id": "546485"}, {"title": "Hydrology of the Great Lakes. By Robert E. Horton in collaboration with C.E. Grunsky.", "author": "Horton, Robert E. 1875-1945.", "id": "1878430"}, {"title": "Water resources paper = Resources hydrauliques, bulletin / Department of the Interior, Water Power Branch.", "author": "", "id": "48522"}, {"title": "L'abb\u00e9 Guillaume Denys de Dieppe (1624-1689), Premier professeur royal d'hydrographie en France.", "author": "Anthiaume, A. 1855-1931.", "id": "1878330"}, {"title": "Service des grandes forces hydrauliques. Etudes glaciologiques ...", "author": "France. Direction des eaux et fore\u0302ts.", "id": "12307141"}, {"title": "Izvestii\ufe20a\ufe21 Gosudarstvennogo gidrologicheskogo instituta. Bulletin de l'Institut hydrologique", "author": "Gosudarstvenny\u012d gidrologicheski\u012d institut (Russia)", "id": "10009940"}, {"title": "The effect of certain Illinois waters on lead / by O.W. Rees and A.L. Elder.", "author": "Rees, O. W.", "id": "101643925"}, {"title": "Bulletin.", "author": "", "id": "545412"}, {"title": "Anuarul hidrografic.", "author": "", "id": "7958760"}, {"title": "Forc\u031cas hydraulicas : trabalhos / Ministerio da Agricultura, Industria e Commercio, Servic\u031co Geologico e Mineralogico do Brasil.", "author": "", "id": "102087791"}]